CHANGELOG.rst
LICENSE
MANIFEST.in
README.rst
setup.py
docs/__init__.py
docs/conf.py
swapify/__init__.py
swapify/cli.py
swapify.egg-info/PKG-INFO
swapify.egg-info/SOURCES.txt
swapify.egg-info/dependency_links.txt
swapify.egg-info/entry_points.txt
swapify.egg-info/requires.txt
swapify.egg-info/top_level.txt