Metadata-Version: 1.1
Name: swapify
Version: 0.1.1
Summary: Make migrations work with swappable models.
Home-page: https://github.com/elbaschid/swapify
Author: Sebastian Vetter
Author-email: sebastian@roadside-developer.com
License: MIT
Platform: linux
Classifier: Environment :: Web Environment
Classifier: Intended Audience :: Developers
Classifier: License :: OSI Approved :: MIT License
Classifier: Operating System :: Unix
Classifier: Programming Language :: Python
